fstep/__init__.py
fstep/app.py
fstep/ast.py
fstep/interpreter.py
fstep/ir.py
fstep/irgen.py
fstep/lexer.py
fstep/parser.py
fstep-0.2.0.dist-info/LICENSE
fstep-0.2.0.dist-info/METADATA
fstep-0.2.0.dist-info/WHEEL
fstep-0.2.0.dist-info/entry_points.txt
fstep-0.2.0.dist-info/top_level.txt
fstep-0.2.0.dist-info/RECORD
