Metadata-Version: 2.1
Name: fstep
Version: 0.2.0
Summary: python mock up pku-minic/first-step
Home-page: https://github.com/allegrofb/fstep
Author: jiang hongyong
Author-email: hongyong_jiang@hotmail.com
License: MIT
Project-URL: Bug Tracker, https://github.com/allegrofb/fstep/issues
Platform: UNKNOWN
Classifier: Programming Language :: Python :: 3
Classifier: License :: OSI Approved :: MIT License
Classifier: Operating System :: OS Independent
Requires-Python: >=3.7
License-File: LICENSE
